shtRipper/__init__.py
shtRipper/debug_read.py
shtRipper/debug_write.py
shtRipper/shtRipper_entry.py
shtRipper/binary/libripperForPython.so
shtRipper/binary/libripperForPythonFor___.so
shtRipper/binary/ripperForPython_32.dll
shtRipper/binary/ripperForPython_64.dll
shtRipper_cpp-1.6.2.dist-info/LICENSE
shtRipper_cpp-1.6.2.dist-info/METADATA
shtRipper_cpp-1.6.2.dist-info/WHEEL
shtRipper_cpp-1.6.2.dist-info/entry_points.txt
shtRipper_cpp-1.6.2.dist-info/top_level.txt
shtRipper_cpp-1.6.2.dist-info/RECORD
