Metadata-Version: 2.1
Name: shtRipper_cpp
Version: 1.6.2
Summary: C++ parser of .sht files.
Home-page: https://github.com/Rezenter/shtRipper_cpp/tree/master/python
Author: Rezenter
Author-email: nisovru@gmail.com
Classifier: Programming Language :: Python :: 3.5
Classifier: License :: OSI Approved :: MIT License
Classifier: Operating System :: Microsoft :: Windows :: Windows 10
Requires-Python: >=3.5
License-File: LICENSE
